pyrocko/__init__.py
pyrocko/_compatibility_modules.py
pyrocko/ahfullgreen.py
pyrocko/ahfullgreen_ext.cpython-314-darwin.so
pyrocko/automap.py
pyrocko/autopick.py
pyrocko/autopick_ext.cpython-314-darwin.so
pyrocko/avl.cpython-314-darwin.so
pyrocko/beachball.py
pyrocko/cake.py
pyrocko/cake_plot.py
pyrocko/catalog.py
pyrocko/color.py
pyrocko/config.py
pyrocko/crust2x2.py
pyrocko/crustdb.py
pyrocko/css.py
pyrocko/datacube.py
pyrocko/datacube_ext.cpython-314-darwin.so
pyrocko/deps.py
pyrocko/dummy_progressbar.py
pyrocko/eikonal_ext.cpython-314-darwin.so
pyrocko/evalresp.py
pyrocko/evalresp_ext.cpython-314-darwin.so
pyrocko/eventdata.py
pyrocko/example.py
pyrocko/file.py
pyrocko/gcf.py
pyrocko/geometry.py
pyrocko/geonames.py
pyrocko/gmtpy.py
pyrocko/gse1.py
pyrocko/gse2_io_wrap.py
pyrocko/gui_util.py
pyrocko/guts.py
pyrocko/guts_agnostic.py
pyrocko/guts_array.py
pyrocko/hamster_pile.py
pyrocko/has_paths.py
pyrocko/himesh.py
pyrocko/hudson.py
pyrocko/icosphere.py
pyrocko/ims.py
pyrocko/ims_ext.cpython-314-darwin.so
pyrocko/info.py
pyrocko/io_common.py
pyrocko/iris_ws.py
pyrocko/kan.py
pyrocko/marker.py
pyrocko/moment_tensor.py
pyrocko/mseed.py
pyrocko/mseed_ext.cpython-314-darwin.so
pyrocko/multitrace.py
pyrocko/orthodrome.py
pyrocko/orthodrome_ext.cpython-314-darwin.so
pyrocko/parimap.py
pyrocko/parstack.py
pyrocko/parstack_ext.cpython-314-darwin.so
pyrocko/pchain.py
pyrocko/pile.py
pyrocko/pile_viewer.py
pyrocko/print_version.py
pyrocko/progress.py
pyrocko/pz.py
pyrocko/rdseed.py
pyrocko/response.py
pyrocko/response_plot.py
pyrocko/sacio.py
pyrocko/segy.py
pyrocko/seisan_response.py
pyrocko/seisan_waveform.py
pyrocko/shadow_pile.py
pyrocko/signal_ext.cpython-314-darwin.so
pyrocko/snuffler.py
pyrocko/snuffling.py
pyrocko/spit.py
pyrocko/suds.py
pyrocko/table.py
pyrocko/tectonics.py
pyrocko/topo.py
pyrocko/trace.py
pyrocko/util.py
pyrocko/util_ext.cpython-314-darwin.so
pyrocko/weeding.py
pyrocko/yaff.py
pyrocko/apps/__init__.py
pyrocko/apps/automap.py
pyrocko/apps/cake.py
pyrocko-2025.12.4.dist-info/licenses/AUTHORS.md
pyrocko-2025.12.4.dist-info/licenses/LICENSE.md
pyrocko-2025.12.4.dist-info/METADATA
pyrocko-2025.12.4.dist-info/WHEEL
pyrocko-2025.12.4.dist-info/entry_points.txt
pyrocko-2025.12.4.dist-info/top_level.txt
pyrocko-2025.12.4.dist-info/RECORD
