Metadata-Version: 2.4
Name: pyrocko
Version: 2025.12.4
Summary: A versatile seismology toolkit for Python.
Author-email: The Pyrocko Developers <info@pyrocko.org>
Maintainer-email: Sebastian Heimann <sebastian.heimann@uni-potsdam.de>
License: GPL-3.0-or-later
Project-URL: homepage, https://pyrocko.org
Project-URL: documentation, https://pyrocko.org/docs
Project-URL: repository, https://git.pyrocko.org/pyrocko/pyrocko
Project-URL: changelog, https://git.pyrocko.org/pyrocko/pyrocko/src/branch/master/CHANGELOG.md
Keywords: seismology,waveform analysis,earthquake modelling,geophysics,geophysical inversion
Classifier: Development Status :: 5 - Production/Stable
Classifier: Intended Audience :: Science/Research
Classifier: Programming Language :: Python :: 3
Classifier: Programming Language :: C
Classifier: Programming Language :: Python :: Implementation :: CPython
Classifier: Operating System :: POSIX
Classifier: Operating System :: MacOS
Classifier: Topic :: Scientific/Engineering
Classifier: Topic :: Scientific/Engineering :: Physics
Classifier: Topic :: Scientific/Engineering :: Visualization
Classifier: Topic :: Scientific/Engineering :: Information Analysis
Classifier: Topic :: Software Development :: Libraries :: Application Frameworks
Requires-Python: >=3.10
License-File: LICENSE.md
License-File: AUTHORS.md
Requires-Dist: numpy<3,>=1.25; python_version > "3.11"
Requires-Dist: numpy<2,>=1.16; python_version <= "3.11"
Requires-Dist: scipy>=1.0
Requires-Dist: pyyaml
Requires-Dist: matplotlib
Requires-Dist: requests
Provides-Extra: gui
Requires-Dist: PyQt5; extra == "gui"
Requires-Dist: vtk; extra == "gui"
Dynamic: license-file
